print_tricks/__init__.py
print_tricks_and_more_alpha-2025.7.28.111.dist-info/METADATA
print_tricks_and_more_alpha-2025.7.28.111.dist-info/WHEEL
print_tricks_and_more_alpha-2025.7.28.111.dist-info/top_level.txt
print_tricks_and_more_alpha-2025.7.28.111.dist-info/RECORD
