Metadata-Version: 2.1
Name: print-tricks-and-more-alpha
Version: 2025.7.28.111
Summary: Simple to use, Powerful Programming! Debugging, Printing, Analysis, and helpful tools!
Author-email: developer-1v <developer_1v@proton.me>
License: MIT
Project-URL: Homepage, https://github.com/developer-1v/print_tricks
Classifier: Programming Language :: Python :: 3
Classifier: Operating System :: OS Independent
Requires-Python: >=3.6
